gitlab/__init__.py
gitlab/__main__.py
gitlab/cli_handler.py
gitlab/packages.py
glpkg-1.4.2.dist-info/licenses/LICENSE.md
glpkg-1.4.2.dist-info/METADATA
glpkg-1.4.2.dist-info/WHEEL
glpkg-1.4.2.dist-info/entry_points.txt
glpkg-1.4.2.dist-info/top_level.txt
glpkg-1.4.2.dist-info/RECORD
