Metadata-Version: 2.4
Name: glpkg
Version: 1.4.2
Summary: Tool to make GitLab generic package registry operations easy.
Author-email: bugproduction <bugproduction@outlook.com>
License-Expression: MIT
Project-URL: Repository, https://gitlab.com/bugproduction/glpkg.git
Keywords: GitLab,packages,registry,generic
Requires-Python: >=3.9
License-File: LICENSE.md
Dynamic: license-file
